Metadata-Version: 2.1
Name: richest
Version: 1.0.0
Summary: A Python package for getting list of Richest people in the world
Home-page: https://github.com/mkfeuhrer/richest
Author: Mohit Khare (mkfeuhrer)
Author-email: mohitfeuhrer@gmail.com
License: MIT
Keywords: richest,programming language ranking,index,programming language,forbes
Platform: UNKNOWN
